actions_testbed/__init__.py
actions_testbed/py.typed
wipac_dev_actions_testbed-1.1.62.dist-info/licenses/LICENSE
wipac_dev_actions_testbed-1.1.62.dist-info/METADATA
wipac_dev_actions_testbed-1.1.62.dist-info/WHEEL
wipac_dev_actions_testbed-1.1.62.dist-info/top_level.txt
wipac_dev_actions_testbed-1.1.62.dist-info/RECORD
