Metadata-Version: 2.4
Name: wipac-dev-actions-testbed
Version: 1.1.62
Summary: A guinea pig for testing `wipac-dev-*-action` packages and workflows -- using python
Author-email: WIPAC Developers <developers@icecube.wisc.edu>
License-Expression: MIT
Project-URL: Homepage, https://pypi.org/project/wipac-dev-actions-testbed/
Project-URL: Tracker, https://github.com/WIPACrepo/wipac-dev-actions-testbed-python/issues
Project-URL: Source, https://github.com/WIPACrepo/wipac-dev-actions-testbed-python
Keywords: WIPAC,CI/CD,gitops,testbed
Classifier: Programming Language :: Python :: 3.12
Classifier: Programming Language :: Python :: 3.13
Requires-Python: <3.14,>=3.12
License-File: LICENSE
Requires-Dist: numpy
Requires-Dist: requests
Dynamic: license-file
